<?xml version="1.0" encoding="utf-8"?>
<controllerConfig>
  <versions>
    <minFirmware>2.3.0.1</minFirmware>
    <actualFirmware>2.3.0.1</actualFirmware>
    <ide>2.5.0.77</ide>
    <updatedGearRatio>1.0.6.1</updatedGearRatio>
  </versions>
  <machineName>MyMachine</machineName>
  <ipAddress>192.168.1.1</ipAddress>
  <subnetMask>255.255.255.0</subnetMask>
  <gateway>192.168.1.1</gateway>
  <driveConversion>
    <axis>
      <axisNumber>3</axisNumber>
      <feedConstant>105</feedConstant>
      <machineCycle>1000</machineCycle>
      <inputRatio>4</inputRatio>
      <outputRatio>1</outputRatio>
      <userUnits>1</userUnits>
      <loadType>0</loadType>
    </axis>
    <axis>
      <axisNumber>4</axisNumber>
      <feedConstant>360</feedConstant>
      <machineCycle>360</machineCycle>
      <inputRatio>4</inputRatio>
      <outputRatio>1</outputRatio>
      <userUnits>4</userUnits>
      <loadType>1</loadType>
    </axis>
    <axis>
      <axisNumber>5</axisNumber>
      <feedConstant>105</feedConstant>
      <machineCycle>1000</machineCycle>
      <inputRatio>4</inputRatio>
      <outputRatio>1</outputRatio>
      <userUnits>1</userUnits>
      <loadType>0</loadType>
    </axis>
    <axis>
      <axisNumber>6</axisNumber>
      <feedConstant>360</feedConstant>
      <machineCycle>360</machineCycle>
      <inputRatio>4</inputRatio>
      <outputRatio>1</outputRatio>
      <userUnits>4</userUnits>
      <loadType>1</loadType>
    </axis>
    <axis>
      <axisNumber>7</axisNumber>
      <feedConstant>105</feedConstant>
      <machineCycle>1000</machineCycle>
      <inputRatio>4</inputRatio>
      <outputRatio>1</outputRatio>
      <userUnits>1</userUnits>
      <loadType>0</loadType>
    </axis>
    <axis>
      <axisNumber>8</axisNumber>
      <feedConstant>360</feedConstant>
      <machineCycle>360</machineCycle>
      <inputRatio>4</inputRatio>
      <outputRatio>1</outputRatio>
      <userUnits>4</userUnits>
      <loadType>1</loadType>
    </axis>
    <axis>
      <axisNumber>9</axisNumber>
      <feedConstant>105</feedConstant>
      <machineCycle>1000</machineCycle>
      <inputRatio>4</inputRatio>
      <outputRatio>1</outputRatio>
      <userUnits>1</userUnits>
      <loadType>0</loadType>
    </axis>
    <axis>
      <axisNumber>10</axisNumber>
      <feedConstant>360</feedConstant>
      <machineCycle>360</machineCycle>
      <inputRatio>4</inputRatio>
      <outputRatio>1</outputRatio>
      <userUnits>4</userUnits>
      <loadType>1</loadType>
    </axis>
    <axis>
      <axisNumber>65</axisNumber>
      <feedConstant>1</feedConstant>
      <machineCycle>1</machineCycle>
      <inputRatio>1</inputRatio>
      <outputRatio>1</outputRatio>
      <userUnits>1</userUnits>
      <loadType>0</loadType>
    </axis>
  </driveConversion>
  <lastIoDeviceId>65530</lastIoDeviceId>
  <deviceNodesProps>
    <nodeProps>
      <nodeType>Axis</nodeType>
      <id>769</id>
      <prop>
        <propNum>2020</propNum>
        <propValue>0</propValue>
      </prop>
    </nodeProps>
    <nodeProps>
      <nodeType>Axis</nodeType>
      <id>1025</id>
      <prop>
        <propNum>2020</propNum>
        <propValue>0</propValue>
      </prop>
    </nodeProps>
    <nodeProps>
      <nodeType>Axis</nodeType>
      <id>1281</id>
      <prop>
        <propNum>2020</propNum>
        <propValue>0</propValue>
      </prop>
    </nodeProps>
    <nodeProps>
      <nodeType>Axis</nodeType>
      <id>1537</id>
      <prop>
        <propNum>2020</propNum>
        <propValue>0</propValue>
      </prop>
    </nodeProps>
    <nodeProps>
      <nodeType>Axis</nodeType>
      <id>1793</id>
      <prop>
        <propNum>2020</propNum>
        <propValue>0</propValue>
      </prop>
    </nodeProps>
    <nodeProps>
      <nodeType>Axis</nodeType>
      <id>2049</id>
      <prop>
        <propNum>2020</propNum>
        <propValue>0</propValue>
      </prop>
    </nodeProps>
    <nodeProps>
      <nodeType>Axis</nodeType>
      <id>2305</id>
      <prop>
        <propNum>2020</propNum>
        <propValue>0</propValue>
      </prop>
    </nodeProps>
    <nodeProps>
      <nodeType>Axis</nodeType>
      <id>2561</id>
      <prop>
        <propNum>2020</propNum>
        <propValue>0</propValue>
      </prop>
    </nodeProps>
    <nodeProps>
      <nodeType>Card</nodeType>
      <id>1</id>
      <prop>
        <propNum>2020</propNum>
        <propValue>0</propValue>
      </prop>
    </nodeProps>
    <nodeProps>
      <nodeType>ModbusTCP</nodeType>
      <id>0</id>
      <prop>
        <propNum>2020</propNum>
        <propValue>0</propValue>
      </prop>
    </nodeProps>
    <nodeProps>
      <nodeType>Ethernet</nodeType>
      <id>0</id>
      <prop>
        <propNum>2020</propNum>
        <propValue>0</propValue>
      </prop>
    </nodeProps>
  </deviceNodesProps>
  <encoderMapping>
    <encoder>
      <slot>1</slot>
      <axisNum>65</axisNum>
    </encoder>
  </encoderMapping>
  <modbusDataBlocks />
  <axisParameters>
    <axisControllerParameters>
      <axisInfo>
        <axisName>AXIS3</axisName>
        <nodeNumber>3</nodeNumber>
        <networkNumber>1</networkNumber>
      </axisInfo>
      <parameter>
        <parameterNumber>1000</parameterNumber>
        <parameterValue>-0.017548799</parameterValue>
      </parameter>
      <parameter>
        <parameterNumber>1001</parameterNumber>
        <parameterValue>-0.02503395</parameterValue>
      </parameter>
      <parameter>
        <parameterNumber>1004</parameterNumber>
        <parameterValue>-0.75</parameterValue>
      </parameter>
      <parameter>
        <parameterNumber>1010</parameterNumber>
        <parameterValue>0</parameterValue>
      </parameter>
      <parameter>
        <parameterNumber>1011</parameterNumber>
        <parameterValue>0</parameterValue>
      </parameter>
      <parameter>
        <parameterNumber>1014</parameterNumber>
        <parameterValue>0</parameterValue>
      </parameter>
      <parameter>
        <parameterNumber>1017</parameterNumber>
        <parameterValue>50</parameterValue>
      </parameter>
      <parameter>
        <parameterNumber>1002</parameterNumber>
        <parameterValue>2.5033E-05</parameterValue>
      </parameter>
      <parameter>
        <parameterNumber>1200</parameterNumber>
        <parameterValue>-1.797693E+308</parameterValue>
      </parameter>
      <parameter>
        <parameterNumber>1201</parameterNumber>
        <parameterValue>1.797693E+308</parameterValue>
      </parameter>
      <parameter>
        <parameterNumber>1300</parameterNumber>
        <parameterValue>0</parameterValue>
      </parameter>
      <parameter>
        <parameterNumber>1301</parameterNumber>
        <parameterValue>0.1</parameterValue>
      </parameter>
      <parameter>
        <parameterNumber>1310</parameterNumber>
        <parameterValue>1</parameterValue>
      </parameter>
      <parameter>
        <parameterNumber>1311</parameterNumber>
        <parameterValue>0</parameterValue>
      </parameter>
      <parameter>
        <parameterNumber>1802</parameterNumber>
        <parameterValue>3332</parameterValue>
      </parameter>
      <parameter>
        <parameterNumber>1007</parameterNumber>
        <parameterValue>0</parameterValue>
      </parameter>
      <parameter>
        <parameterNumber>1008</parameterNumber>
        <parameterValue>105</parameterValue>
      </parameter>
      <parameter>
        <parameterNumber>1009</parameterNumber>
        <parameterValue>AXIS3</parameterValue>
      </parameter>
      <parameter>
        <parameterNumber>1013</parameterNumber>
        <parameterValue>1</parameterValue>
      </parameter>
      <parameter>
        <parameterNumber>1015</parameterNumber>
        <parameterValue>1</parameterValue>
      </parameter>
      <parameter>
        <parameterNumber>1016</parameterNumber>
        <parameterValue>50</parameterValue>
      </parameter>
      <parameter>
        <parameterNumber>1018</parameterNumber>
        <parameterValue>3</parameterValue>
      </parameter>
      <parameter>
        <parameterNumber>1019</parameterNumber>
        <parameterValue>SGDV-2R1F21A002000</parameterValue>
      </parameter>
      <parameter>
        <parameterNumber>1020</parameterNumber>
        <parameterValue>0</parameterValue>
      </parameter>
      <parameter>
        <parameterNumber>1021</parameterNumber>
        <parameterValue>rotary</parameterValue>
      </parameter>
      <parameter>
        <parameterNumber>1022</parameterNumber>
        <parameterValue>200</parameterValue>
      </parameter>
      <parameter>
        <parameterNumber>1023</parameterNumber>
        <parameterValue>SGMJV-C2A3A61</parameterValue>
      </parameter>
      <parameter>
        <parameterNumber>1024</parameterNumber>
        <parameterValue>rotary</parameterValue>
      </parameter>
      <parameter>
        <parameterNumber>1025</parameterNumber>
        <parameterValue>150</parameterValue>
      </parameter>
      <parameter>
        <parameterNumber>1026</parameterNumber>
        <parameterValue>absolute</parameterValue>
      </parameter>
      <parameter>
        <parameterNumber>1027</parameterNumber>
        <parameterValue>1048576</parameterValue>
      </parameter>
      <parameter>
        <parameterNumber>1028</parameterNumber>
        <parameterValue>1</parameterValue>
      </parameter>
      <parameter>
        <parameterNumber>1031</parameterNumber>
        <parameterValue>3</parameterValue>
      </parameter>
      <parameter>
        <parameterNumber>1033</parameterNumber>
        <parameterValue>1000</parameterValue>
      </parameter>
      <parameter>
        <parameterNumber>1034</parameterNumber>
        <parameterValue>4</parameterValue>
      </parameter>
      <parameter>
        <parameterNumber>1035</parameterNumber>
        <parameterValue>0</parameterValue>
      </parameter>
      <parameter>
        <parameterNumber>1036</parameterNumber>
        <parameterValue>0.477000000</parameterValue>
      </parameter>
      <parameter>
        <parameterNumber>1037</parameterNumber>
        <parameterValue>3000</parameterValue>
      </parameter>
      <parameter>
        <parameterNumber>1048</parameterNumber>
        <parameterValue>0</parameterValue>
      </parameter>
      <parameter>
        <parameterNumber>2020</parameterNumber>
        <parameterValue>0</parameterValue>
      </parameter>
      <parameter>
        <parameterNumber>2028</parameterNumber>
        <parameterValue>300</parameterValue>
      </parameter>
    </axisControllerParameters>
    <axisControllerParameters>
      <axisInfo>
        <axisName>AXIS4</axisName>
        <nodeNumber>4</nodeNumber>
        <networkNumber>1</networkNumber>
      </axisInfo>
      <parameter>
        <parameterNumber>1000</parameterNumber>
        <parameterValue>0</parameterValue>
      </parameter>
      <parameter>
        <parameterNumber>1001</parameterNumber>
        <parameterValue>0.085830688</parameterValue>
      </parameter>
      <parameter>
        <parameterNumber>1004</parameterNumber>
        <parameterValue>-0.68</parameterValue>
      </parameter>
      <parameter>
        <parameterNumber>1010</parameterNumber>
        <parameterValue>0</parameterValue>
      </parameter>
      <parameter>
        <parameterNumber>1011</parameterNumber>
        <parameterValue>0</parameterValue>
      </parameter>
      <parameter>
        <parameterNumber>1014</parameterNumber>
        <parameterValue>0</parameterValue>
      </parameter>
      <parameter>
        <parameterNumber>1017</parameterNumber>
        <parameterValue>50</parameterValue>
      </parameter>
      <parameter>
        <parameterNumber>1002</parameterNumber>
        <parameterValue>0</parameterValue>
      </parameter>
      <parameter>
        <parameterNumber>1200</parameterNumber>
        <parameterValue>-1.797693E+308</parameterValue>
      </parameter>
      <parameter>
        <parameterNumber>1201</parameterNumber>
        <parameterValue>1.797693E+308</parameterValue>
      </parameter>
      <parameter>
        <parameterNumber>1300</parameterNumber>
        <parameterValue>0</parameterValue>
      </parameter>
      <parameter>
        <parameterNumber>1301</parameterNumber>
        <parameterValue>0.1</parameterValue>
      </parameter>
      <parameter>
        <parameterNumber>1310</parameterNumber>
        <parameterValue>1</parameterValue>
      </parameter>
      <parameter>
        <parameterNumber>1311</parameterNumber>
        <parameterValue>0</parameterValue>
      </parameter>
      <parameter>
        <parameterNumber>1802</parameterNumber>
        <parameterValue>2780</parameterValue>
      </parameter>
      <parameter>
        <parameterNumber>1007</parameterNumber>
        <parameterValue>1</parameterValue>
      </parameter>
      <parameter>
        <parameterNumber>1008</parameterNumber>
        <parameterValue>360</parameterValue>
      </parameter>
      <parameter>
        <parameterNumber>1009</parameterNumber>
        <parameterValue>AXIS4</parameterValue>
      </parameter>
      <parameter>
        <parameterNumber>1013</parameterNumber>
        <parameterValue>4</parameterValue>
      </parameter>
      <parameter>
        <parameterNumber>1015</parameterNumber>
        <parameterValue>1</parameterValue>
      </parameter>
      <parameter>
        <parameterNumber>1016</parameterNumber>
        <parameterValue>50</parameterValue>
      </parameter>
      <parameter>
        <parameterNumber>1018</parameterNumber>
        <parameterValue>4</parameterValue>
      </parameter>
      <parameter>
        <parameterNumber>1019</parameterNumber>
        <parameterValue>SGDV-R90F21A002000</parameterValue>
      </parameter>
      <parameter>
        <parameterNumber>1020</parameterNumber>
        <parameterValue>0</parameterValue>
      </parameter>
      <parameter>
        <parameterNumber>1021</parameterNumber>
        <parameterValue>rotary</parameterValue>
      </parameter>
      <parameter>
        <parameterNumber>1022</parameterNumber>
        <parameterValue>100</parameterValue>
      </parameter>
      <parameter>
        <parameterNumber>1023</parameterNumber>
        <parameterValue>SGMJV-01A3A61</parameterValue>
      </parameter>
      <parameter>
        <parameterNumber>1024</parameterNumber>
        <parameterValue>rotary</parameterValue>
      </parameter>
      <parameter>
        <parameterNumber>1025</parameterNumber>
        <parameterValue>100</parameterValue>
      </parameter>
      <parameter>
        <parameterNumber>1026</parameterNumber>
        <parameterValue>absolute</parameterValue>
      </parameter>
      <parameter>
        <parameterNumber>1027</parameterNumber>
        <parameterValue>1048576</parameterValue>
      </parameter>
      <parameter>
        <parameterNumber>1028</parameterNumber>
        <parameterValue>1</parameterValue>
      </parameter>
      <parameter>
        <parameterNumber>1031</parameterNumber>
        <parameterValue>4</parameterValue>
      </parameter>
      <parameter>
        <parameterNumber>1033</parameterNumber>
        <parameterValue>360</parameterValue>
      </parameter>
      <parameter>
        <parameterNumber>1034</parameterNumber>
        <parameterValue>4</parameterValue>
      </parameter>
      <parameter>
        <parameterNumber>1035</parameterNumber>
        <parameterValue>0</parameterValue>
      </parameter>
      <parameter>
        <parameterNumber>1036</parameterNumber>
        <parameterValue>0.318000000</parameterValue>
      </parameter>
      <parameter>
        <parameterNumber>1037</parameterNumber>
        <parameterValue>3000</parameterValue>
      </parameter>
      <parameter>
        <parameterNumber>1048</parameterNumber>
        <parameterValue>0</parameterValue>
      </parameter>
      <parameter>
        <parameterNumber>2020</parameterNumber>
        <parameterValue>0</parameterValue>
      </parameter>
      <parameter>
        <parameterNumber>2028</parameterNumber>
        <parameterValue>300</parameterValue>
      </parameter>
    </axisControllerParameters>
    <axisControllerParameters>
      <axisInfo>
        <axisName>AXIS5</axisName>
        <nodeNumber>5</nodeNumber>
        <networkNumber>1</networkNumber>
      </axisInfo>
      <parameter>
        <parameterNumber>1000</parameterNumber>
        <parameterValue>0.014619827</parameterValue>
      </parameter>
      <parameter>
        <parameterNumber>1001</parameterNumber>
        <parameterValue>0</parameterValue>
      </parameter>
      <parameter>
        <parameterNumber>1004</parameterNumber>
        <parameterValue>2.649999999</parameterValue>
      </parameter>
      <parameter>
        <parameterNumber>1010</parameterNumber>
        <parameterValue>0</parameterValue>
      </parameter>
      <parameter>
        <parameterNumber>1011</parameterNumber>
        <parameterValue>0</parameterValue>
      </parameter>
      <parameter>
        <parameterNumber>1014</parameterNumber>
        <parameterValue>0</parameterValue>
      </parameter>
      <parameter>
        <parameterNumber>1017</parameterNumber>
        <parameterValue>50</parameterValue>
      </parameter>
      <parameter>
        <parameterNumber>1002</parameterNumber>
        <parameterValue>0</parameterValue>
      </parameter>
      <parameter>
        <parameterNumber>1200</parameterNumber>
        <parameterValue>-1.797693E+308</parameterValue>
      </parameter>
      <parameter>
        <parameterNumber>1201</parameterNumber>
        <parameterValue>1.797693E+308</parameterValue>
      </parameter>
      <parameter>
        <parameterNumber>1300</parameterNumber>
        <parameterValue>0</parameterValue>
      </parameter>
      <parameter>
        <parameterNumber>1301</parameterNumber>
        <parameterValue>0.1</parameterValue>
      </parameter>
      <parameter>
        <parameterNumber>1310</parameterNumber>
        <parameterValue>1</parameterValue>
      </parameter>
      <parameter>
        <parameterNumber>1311</parameterNumber>
        <parameterValue>0</parameterValue>
      </parameter>
      <parameter>
        <parameterNumber>1802</parameterNumber>
        <parameterValue>2964</parameterValue>
      </parameter>
      <parameter>
        <parameterNumber>1007</parameterNumber>
        <parameterValue>0</parameterValue>
      </parameter>
      <parameter>
        <parameterNumber>1008</parameterNumber>
        <parameterValue>105</parameterValue>
      </parameter>
      <parameter>
        <parameterNumber>1009</parameterNumber>
        <parameterValue>AXIS5</parameterValue>
      </parameter>
      <parameter>
        <parameterNumber>1013</parameterNumber>
        <parameterValue>1</parameterValue>
      </parameter>
      <parameter>
        <parameterNumber>1015</parameterNumber>
        <parameterValue>1</parameterValue>
      </parameter>
      <parameter>
        <parameterNumber>1016</parameterNumber>
        <parameterValue>50</parameterValue>
      </parameter>
      <parameter>
        <parameterNumber>1018</parameterNumber>
        <parameterValue>5</parameterValue>
      </parameter>
      <parameter>
        <parameterNumber>1019</parameterNumber>
        <parameterValue>SGDV-2R1F21A002000</parameterValue>
      </parameter>
      <parameter>
        <parameterNumber>1020</parameterNumber>
        <parameterValue>0</parameterValue>
      </parameter>
      <parameter>
        <parameterNumber>1021</parameterNumber>
        <parameterValue>rotary</parameterValue>
      </parameter>
      <parameter>
        <parameterNumber>1022</parameterNumber>
        <parameterValue>200</parameterValue>
      </parameter>
      <parameter>
        <parameterNumber>1023</parameterNumber>
        <parameterValue>SGMJV-C2A3A61</parameterValue>
      </parameter>
      <parameter>
        <parameterNumber>1024</parameterNumber>
        <parameterValue>rotary</parameterValue>
      </parameter>
      <parameter>
        <parameterNumber>1025</parameterNumber>
        <parameterValue>150</parameterValue>
      </parameter>
      <parameter>
        <parameterNumber>1026</parameterNumber>
        <parameterValue>absolute</parameterValue>
      </parameter>
      <parameter>
        <parameterNumber>1027</parameterNumber>
        <parameterValue>1048576</parameterValue>
      </parameter>
      <parameter>
        <parameterNumber>1028</parameterNumber>
        <parameterValue>1</parameterValue>
      </parameter>
      <parameter>
        <parameterNumber>1031</parameterNumber>
        <parameterValue>5</parameterValue>
      </parameter>
      <parameter>
        <parameterNumber>1033</parameterNumber>
        <parameterValue>1000</parameterValue>
      </parameter>
      <parameter>
        <parameterNumber>1034</parameterNumber>
        <parameterValue>4</parameterValue>
      </parameter>
      <parameter>
        <parameterNumber>1035</parameterNumber>
        <parameterValue>0</parameterValue>
      </parameter>
      <parameter>
        <parameterNumber>1036</parameterNumber>
        <parameterValue>0.477000000</parameterValue>
      </parameter>
      <parameter>
        <parameterNumber>1037</parameterNumber>
        <parameterValue>3000</parameterValue>
      </parameter>
      <parameter>
        <parameterNumber>1048</parameterNumber>
        <parameterValue>0</parameterValue>
      </parameter>
      <parameter>
        <parameterNumber>2020</parameterNumber>
        <parameterValue>0</parameterValue>
      </parameter>
      <parameter>
        <parameterNumber>2028</parameterNumber>
        <parameterValue>300</parameterValue>
      </parameter>
    </axisControllerParameters>
    <axisControllerParameters>
      <axisInfo>
        <axisName>AXIS6</axisName>
        <nodeNumber>6</nodeNumber>
        <networkNumber>1</networkNumber>
      </axisInfo>
      <parameter>
        <parameterNumber>1000</parameterNumber>
        <parameterValue>359.9779415</parameterValue>
      </parameter>
      <parameter>
        <parameterNumber>1001</parameterNumber>
        <parameterValue>0</parameterValue>
      </parameter>
      <parameter>
        <parameterNumber>1004</parameterNumber>
        <parameterValue>0</parameterValue>
      </parameter>
      <parameter>
        <parameterNumber>1010</parameterNumber>
        <parameterValue>0</parameterValue>
      </parameter>
      <parameter>
        <parameterNumber>1011</parameterNumber>
        <parameterValue>0</parameterValue>
      </parameter>
      <parameter>
        <parameterNumber>1014</parameterNumber>
        <parameterValue>0</parameterValue>
      </parameter>
      <parameter>
        <parameterNumber>1017</parameterNumber>
        <parameterValue>50</parameterValue>
      </parameter>
      <parameter>
        <parameterNumber>1002</parameterNumber>
        <parameterValue>0</parameterValue>
      </parameter>
      <parameter>
        <parameterNumber>1200</parameterNumber>
        <parameterValue>-1.797693E+308</parameterValue>
      </parameter>
      <parameter>
        <parameterNumber>1201</parameterNumber>
        <parameterValue>1.797693E+308</parameterValue>
      </parameter>
      <parameter>
        <parameterNumber>1300</parameterNumber>
        <parameterValue>0</parameterValue>
      </parameter>
      <parameter>
        <parameterNumber>1301</parameterNumber>
        <parameterValue>0.1</parameterValue>
      </parameter>
      <parameter>
        <parameterNumber>1310</parameterNumber>
        <parameterValue>1</parameterValue>
      </parameter>
      <parameter>
        <parameterNumber>1311</parameterNumber>
        <parameterValue>0</parameterValue>
      </parameter>
      <parameter>
        <parameterNumber>1802</parameterNumber>
        <parameterValue>2780</parameterValue>
      </parameter>
      <parameter>
        <parameterNumber>1007</parameterNumber>
        <parameterValue>1</parameterValue>
      </parameter>
      <parameter>
        <parameterNumber>1008</parameterNumber>
        <parameterValue>360</parameterValue>
      </parameter>
      <parameter>
        <parameterNumber>1009</parameterNumber>
        <parameterValue>AXIS6</parameterValue>
      </parameter>
      <parameter>
        <parameterNumber>1013</parameterNumber>
        <parameterValue>4</parameterValue>
      </parameter>
      <parameter>
        <parameterNumber>1015</parameterNumber>
        <parameterValue>1</parameterValue>
      </parameter>
      <parameter>
        <parameterNumber>1016</parameterNumber>
        <parameterValue>50</parameterValue>
      </parameter>
      <parameter>
        <parameterNumber>1018</parameterNumber>
        <parameterValue>6</parameterValue>
      </parameter>
      <parameter>
        <parameterNumber>1019</parameterNumber>
        <parameterValue>SGDV-R90F21A002000</parameterValue>
      </parameter>
      <parameter>
        <parameterNumber>1020</parameterNumber>
        <parameterValue>0</parameterValue>
      </parameter>
      <parameter>
        <parameterNumber>1021</parameterNumber>
        <parameterValue>rotary</parameterValue>
      </parameter>
      <parameter>
        <parameterNumber>1022</parameterNumber>
        <parameterValue>100</parameterValue>
      </parameter>
      <parameter>
        <parameterNumber>1023</parameterNumber>
        <parameterValue>SGMJV-01A3A61</parameterValue>
      </parameter>
      <parameter>
        <parameterNumber>1024</parameterNumber>
        <parameterValue>rotary</parameterValue>
      </parameter>
      <parameter>
        <parameterNumber>1025</parameterNumber>
        <parameterValue>100</parameterValue>
      </parameter>
      <parameter>
        <parameterNumber>1026</parameterNumber>
        <parameterValue>absolute</parameterValue>
      </parameter>
      <parameter>
        <parameterNumber>1027</parameterNumber>
        <parameterValue>1048576</parameterValue>
      </parameter>
      <parameter>
        <parameterNumber>1028</parameterNumber>
        <parameterValue>1</parameterValue>
      </parameter>
      <parameter>
        <parameterNumber>1031</parameterNumber>
        <parameterValue>6</parameterValue>
      </parameter>
      <parameter>
        <parameterNumber>1033</parameterNumber>
        <parameterValue>360</parameterValue>
      </parameter>
      <parameter>
        <parameterNumber>1034</parameterNumber>
        <parameterValue>4</parameterValue>
      </parameter>
      <parameter>
        <parameterNumber>1035</parameterNumber>
        <parameterValue>0</parameterValue>
      </parameter>
      <parameter>
        <parameterNumber>1036</parameterNumber>
        <parameterValue>0.318000000</parameterValue>
      </parameter>
      <parameter>
        <parameterNumber>1037</parameterNumber>
        <parameterValue>3000</parameterValue>
      </parameter>
      <parameter>
        <parameterNumber>1048</parameterNumber>
        <parameterValue>0</parameterValue>
      </parameter>
      <parameter>
        <parameterNumber>2020</parameterNumber>
        <parameterValue>0</parameterValue>
      </parameter>
      <parameter>
        <parameterNumber>2028</parameterNumber>
        <parameterValue>300</parameterValue>
      </parameter>
    </axisControllerParameters>
    <axisControllerParameters>
      <axisInfo>
        <axisName>AXIS7</axisName>
        <nodeNumber>7</nodeNumber>
        <networkNumber>1</networkNumber>
      </axisInfo>
      <parameter>
        <parameterNumber>1000</parameterNumber>
        <parameterValue>-385.2769839</parameterValue>
      </parameter>
      <parameter>
        <parameterNumber>1001</parameterNumber>
        <parameterValue>0</parameterValue>
      </parameter>
      <parameter>
        <parameterNumber>1004</parameterNumber>
        <parameterValue>-1.06</parameterValue>
      </parameter>
      <parameter>
        <parameterNumber>1010</parameterNumber>
        <parameterValue>0</parameterValue>
      </parameter>
      <parameter>
        <parameterNumber>1011</parameterNumber>
        <parameterValue>0</parameterValue>
      </parameter>
      <parameter>
        <parameterNumber>1014</parameterNumber>
        <parameterValue>0</parameterValue>
      </parameter>
      <parameter>
        <parameterNumber>1017</parameterNumber>
        <parameterValue>50</parameterValue>
      </parameter>
      <parameter>
        <parameterNumber>1002</parameterNumber>
        <parameterValue>0</parameterValue>
      </parameter>
      <parameter>
        <parameterNumber>1200</parameterNumber>
        <parameterValue>-1.797693E+308</parameterValue>
      </parameter>
      <parameter>
        <parameterNumber>1201</parameterNumber>
        <parameterValue>1.797693E+308</parameterValue>
      </parameter>
      <parameter>
        <parameterNumber>1300</parameterNumber>
        <parameterValue>0</parameterValue>
      </parameter>
      <parameter>
        <parameterNumber>1301</parameterNumber>
        <parameterValue>0.1</parameterValue>
      </parameter>
      <parameter>
        <parameterNumber>1310</parameterNumber>
        <parameterValue>1</parameterValue>
      </parameter>
      <parameter>
        <parameterNumber>1311</parameterNumber>
        <parameterValue>0</parameterValue>
      </parameter>
      <parameter>
        <parameterNumber>1802</parameterNumber>
        <parameterValue>2596</parameterValue>
      </parameter>
      <parameter>
        <parameterNumber>1007</parameterNumber>
        <parameterValue>0</parameterValue>
      </parameter>
      <parameter>
        <parameterNumber>1008</parameterNumber>
        <parameterValue>105</parameterValue>
      </parameter>
      <parameter>
        <parameterNumber>1009</parameterNumber>
        <parameterValue>AXIS7</parameterValue>
      </parameter>
      <parameter>
        <parameterNumber>1013</parameterNumber>
        <parameterValue>1</parameterValue>
      </parameter>
      <parameter>
        <parameterNumber>1015</parameterNumber>
        <parameterValue>1</parameterValue>
      </parameter>
      <parameter>
        <parameterNumber>1016</parameterNumber>
        <parameterValue>50</parameterValue>
      </parameter>
      <parameter>
        <parameterNumber>1018</parameterNumber>
        <parameterValue>7</parameterValue>
      </parameter>
      <parameter>
        <parameterNumber>1019</parameterNumber>
        <parameterValue>SGDV-2R1F21A002000</parameterValue>
      </parameter>
      <parameter>
        <parameterNumber>1020</parameterNumber>
        <parameterValue>0</parameterValue>
      </parameter>
      <parameter>
        <parameterNumber>1021</parameterNumber>
        <parameterValue>rotary</parameterValue>
      </parameter>
      <parameter>
        <parameterNumber>1022</parameterNumber>
        <parameterValue>200</parameterValue>
      </parameter>
      <parameter>
        <parameterNumber>1023</parameterNumber>
        <parameterValue>SGMJV-C2A3A61</parameterValue>
      </parameter>
      <parameter>
        <parameterNumber>1024</parameterNumber>
        <parameterValue>rotary</parameterValue>
      </parameter>
      <parameter>
        <parameterNumber>1025</parameterNumber>
        <parameterValue>150</parameterValue>
      </parameter>
      <parameter>
        <parameterNumber>1026</parameterNumber>
        <parameterValue>absolute</parameterValue>
      </parameter>
      <parameter>
        <parameterNumber>1027</parameterNumber>
        <parameterValue>1048576</parameterValue>
      </parameter>
      <parameter>
        <parameterNumber>1028</parameterNumber>
        <parameterValue>1</parameterValue>
      </parameter>
      <parameter>
        <parameterNumber>1031</parameterNumber>
        <parameterValue>7</parameterValue>
      </parameter>
      <parameter>
        <parameterNumber>1033</parameterNumber>
        <parameterValue>1000</parameterValue>
      </parameter>
      <parameter>
        <parameterNumber>1034</parameterNumber>
        <parameterValue>4</parameterValue>
      </parameter>
      <parameter>
        <parameterNumber>1035</parameterNumber>
        <parameterValue>0</parameterValue>
      </parameter>
      <parameter>
        <parameterNumber>1036</parameterNumber>
        <parameterValue>0.477000000</parameterValue>
      </parameter>
      <parameter>
        <parameterNumber>1037</parameterNumber>
        <parameterValue>3000</parameterValue>
      </parameter>
      <parameter>
        <parameterNumber>1048</parameterNumber>
        <parameterValue>0</parameterValue>
      </parameter>
      <parameter>
        <parameterNumber>2020</parameterNumber>
        <parameterValue>0</parameterValue>
      </parameter>
      <parameter>
        <parameterNumber>2028</parameterNumber>
        <parameterValue>300</parameterValue>
      </parameter>
    </axisControllerParameters>
    <axisControllerParameters>
      <axisInfo>
        <axisName>AXIS8</axisName>
        <nodeNumber>8</nodeNumber>
        <networkNumber>1</networkNumber>
      </axisInfo>
      <parameter>
        <parameterNumber>1000</parameterNumber>
        <parameterValue>325.3732395</parameterValue>
      </parameter>
      <parameter>
        <parameterNumber>1001</parameterNumber>
        <parameterValue>142.3931121</parameterValue>
      </parameter>
      <parameter>
        <parameterNumber>1004</parameterNumber>
        <parameterValue>7.98</parameterValue>
      </parameter>
      <parameter>
        <parameterNumber>1010</parameterNumber>
        <parameterValue>0</parameterValue>
      </parameter>
      <parameter>
        <parameterNumber>1011</parameterNumber>
        <parameterValue>0</parameterValue>
      </parameter>
      <parameter>
        <parameterNumber>1014</parameterNumber>
        <parameterValue>0</parameterValue>
      </parameter>
      <parameter>
        <parameterNumber>1017</parameterNumber>
        <parameterValue>50</parameterValue>
      </parameter>
      <parameter>
        <parameterNumber>1002</parameterNumber>
        <parameterValue>2.83000946</parameterValue>
      </parameter>
      <parameter>
        <parameterNumber>1200</parameterNumber>
        <parameterValue>-1.797693E+308</parameterValue>
      </parameter>
      <parameter>
        <parameterNumber>1201</parameterNumber>
        <parameterValue>1.797693E+308</parameterValue>
      </parameter>
      <parameter>
        <parameterNumber>1300</parameterNumber>
        <parameterValue>0</parameterValue>
      </parameter>
      <parameter>
        <parameterNumber>1301</parameterNumber>
        <parameterValue>0.1</parameterValue>
      </parameter>
      <parameter>
        <parameterNumber>1310</parameterNumber>
        <parameterValue>1</parameterValue>
      </parameter>
      <parameter>
        <parameterNumber>1311</parameterNumber>
        <parameterValue>0</parameterValue>
      </parameter>
      <parameter>
        <parameterNumber>1802</parameterNumber>
        <parameterValue>2416</parameterValue>
      </parameter>
      <parameter>
        <parameterNumber>1007</parameterNumber>
        <parameterValue>1</parameterValue>
      </parameter>
      <parameter>
        <parameterNumber>1008</parameterNumber>
        <parameterValue>360</parameterValue>
      </parameter>
      <parameter>
        <parameterNumber>1009</parameterNumber>
        <parameterValue>AXIS8</parameterValue>
      </parameter>
      <parameter>
        <parameterNumber>1013</parameterNumber>
        <parameterValue>4</parameterValue>
      </parameter>
      <parameter>
        <parameterNumber>1015</parameterNumber>
        <parameterValue>1</parameterValue>
      </parameter>
      <parameter>
        <parameterNumber>1016</parameterNumber>
        <parameterValue>50</parameterValue>
      </parameter>
      <parameter>
        <parameterNumber>1018</parameterNumber>
        <parameterValue>8</parameterValue>
      </parameter>
      <parameter>
        <parameterNumber>1019</parameterNumber>
        <parameterValue>SGDV-R90F21A002000</parameterValue>
      </parameter>
      <parameter>
        <parameterNumber>1020</parameterNumber>
        <parameterValue>0</parameterValue>
      </parameter>
      <parameter>
        <parameterNumber>1021</parameterNumber>
        <parameterValue>rotary</parameterValue>
      </parameter>
      <parameter>
        <parameterNumber>1022</parameterNumber>
        <parameterValue>100</parameterValue>
      </parameter>
      <parameter>
        <parameterNumber>1023</parameterNumber>
        <parameterValue>SGMJV-01A3A61</parameterValue>
      </parameter>
      <parameter>
        <parameterNumber>1024</parameterNumber>
        <parameterValue>rotary</parameterValue>
      </parameter>
      <parameter>
        <parameterNumber>1025</parameterNumber>
        <parameterValue>100</parameterValue>
      </parameter>
      <parameter>
        <parameterNumber>1026</parameterNumber>
        <parameterValue>absolute</parameterValue>
      </parameter>
      <parameter>
        <parameterNumber>1027</parameterNumber>
        <parameterValue>1048576</parameterValue>
      </parameter>
      <parameter>
        <parameterNumber>1028</parameterNumber>
        <parameterValue>1</parameterValue>
      </parameter>
      <parameter>
        <parameterNumber>1031</parameterNumber>
        <parameterValue>8</parameterValue>
      </parameter>
      <parameter>
        <parameterNumber>1033</parameterNumber>
        <parameterValue>360</parameterValue>
      </parameter>
      <parameter>
        <parameterNumber>1034</parameterNumber>
        <parameterValue>4</parameterValue>
      </parameter>
      <parameter>
        <parameterNumber>1035</parameterNumber>
        <parameterValue>0</parameterValue>
      </parameter>
      <parameter>
        <parameterNumber>1036</parameterNumber>
        <parameterValue>0.318000000</parameterValue>
      </parameter>
      <parameter>
        <parameterNumber>1037</parameterNumber>
        <parameterValue>3000</parameterValue>
      </parameter>
      <parameter>
        <parameterNumber>1048</parameterNumber>
        <parameterValue>0</parameterValue>
      </parameter>
      <parameter>
        <parameterNumber>2020</parameterNumber>
        <parameterValue>0</parameterValue>
      </parameter>
      <parameter>
        <parameterNumber>2028</parameterNumber>
        <parameterValue>300</parameterValue>
      </parameter>
    </axisControllerParameters>
    <axisControllerParameters>
      <axisInfo>
        <axisName>AXIS9</axisName>
        <nodeNumber>9</nodeNumber>
        <networkNumber>1</networkNumber>
      </axisInfo>
      <parameter>
        <parameterNumber>1000</parameterNumber>
        <parameterValue>0.006633996</parameterValue>
      </parameter>
      <parameter>
        <parameterNumber>1001</parameterNumber>
        <parameterValue>0.050067901</parameterValue>
      </parameter>
      <parameter>
        <parameterNumber>1004</parameterNumber>
        <parameterValue>1.57</parameterValue>
      </parameter>
      <parameter>
        <parameterNumber>1010</parameterNumber>
        <parameterValue>0</parameterValue>
      </parameter>
      <parameter>
        <parameterNumber>1011</parameterNumber>
        <parameterValue>0</parameterValue>
      </parameter>
      <parameter>
        <parameterNumber>1014</parameterNumber>
        <parameterValue>0</parameterValue>
      </parameter>
      <parameter>
        <parameterNumber>1017</parameterNumber>
        <parameterValue>50</parameterValue>
      </parameter>
      <parameter>
        <parameterNumber>1002</parameterNumber>
        <parameterValue>-2.5033E-05</parameterValue>
      </parameter>
      <parameter>
        <parameterNumber>1200</parameterNumber>
        <parameterValue>-1.797693E+308</parameterValue>
      </parameter>
      <parameter>
        <parameterNumber>1201</parameterNumber>
        <parameterValue>1.797693E+308</parameterValue>
      </parameter>
      <parameter>
        <parameterNumber>1300</parameterNumber>
        <parameterValue>0</parameterValue>
      </parameter>
      <parameter>
        <parameterNumber>1301</parameterNumber>
        <parameterValue>0.1</parameterValue>
      </parameter>
      <parameter>
        <parameterNumber>1310</parameterNumber>
        <parameterValue>1</parameterValue>
      </parameter>
      <parameter>
        <parameterNumber>1311</parameterNumber>
        <parameterValue>0</parameterValue>
      </parameter>
      <parameter>
        <parameterNumber>1802</parameterNumber>
        <parameterValue>2232</parameterValue>
      </parameter>
      <parameter>
        <parameterNumber>1007</parameterNumber>
        <parameterValue>0</parameterValue>
      </parameter>
      <parameter>
        <parameterNumber>1008</parameterNumber>
        <parameterValue>105</parameterValue>
      </parameter>
      <parameter>
        <parameterNumber>1009</parameterNumber>
        <parameterValue>AXIS9</parameterValue>
      </parameter>
      <parameter>
        <parameterNumber>1013</parameterNumber>
        <parameterValue>1</parameterValue>
      </parameter>
      <parameter>
        <parameterNumber>1015</parameterNumber>
        <parameterValue>1</parameterValue>
      </parameter>
      <parameter>
        <parameterNumber>1016</parameterNumber>
        <parameterValue>50</parameterValue>
      </parameter>
      <parameter>
        <parameterNumber>1018</parameterNumber>
        <parameterValue>9</parameterValue>
      </parameter>
      <parameter>
        <parameterNumber>1019</parameterNumber>
        <parameterValue>SGDV-2R1F21A002000</parameterValue>
      </parameter>
      <parameter>
        <parameterNumber>1020</parameterNumber>
        <parameterValue>0</parameterValue>
      </parameter>
      <parameter>
        <parameterNumber>1021</parameterNumber>
        <parameterValue>rotary</parameterValue>
      </parameter>
      <parameter>
        <parameterNumber>1022</parameterNumber>
        <parameterValue>200</parameterValue>
      </parameter>
      <parameter>
        <parameterNumber>1023</parameterNumber>
        <parameterValue>SGMJV-C2A3A61</parameterValue>
      </parameter>
      <parameter>
        <parameterNumber>1024</parameterNumber>
        <parameterValue>rotary</parameterValue>
      </parameter>
      <parameter>
        <parameterNumber>1025</parameterNumber>
        <parameterValue>150</parameterValue>
      </parameter>
      <parameter>
        <parameterNumber>1026</parameterNumber>
        <parameterValue>absolute</parameterValue>
      </parameter>
      <parameter>
        <parameterNumber>1027</parameterNumber>
        <parameterValue>1048576</parameterValue>
      </parameter>
      <parameter>
        <parameterNumber>1028</parameterNumber>
        <parameterValue>1</parameterValue>
      </parameter>
      <parameter>
        <parameterNumber>1031</parameterNumber>
        <parameterValue>9</parameterValue>
      </parameter>
      <parameter>
        <parameterNumber>1033</parameterNumber>
        <parameterValue>1000</parameterValue>
      </parameter>
      <parameter>
        <parameterNumber>1034</parameterNumber>
        <parameterValue>4</parameterValue>
      </parameter>
      <parameter>
        <parameterNumber>1035</parameterNumber>
        <parameterValue>0</parameterValue>
      </parameter>
      <parameter>
        <parameterNumber>1036</parameterNumber>
        <parameterValue>0.477000000</parameterValue>
      </parameter>
      <parameter>
        <parameterNumber>1037</parameterNumber>
        <parameterValue>3000</parameterValue>
      </parameter>
      <parameter>
        <parameterNumber>1048</parameterNumber>
        <parameterValue>0</parameterValue>
      </parameter>
      <parameter>
        <parameterNumber>2020</parameterNumber>
        <parameterValue>0</parameterValue>
      </parameter>
      <parameter>
        <parameterNumber>2028</parameterNumber>
        <parameterValue>300</parameterValue>
      </parameter>
    </axisControllerParameters>
    <axisControllerParameters>
      <axisInfo>
        <axisName>AXIS10</axisName>
        <nodeNumber>10</nodeNumber>
        <networkNumber>1</networkNumber>
      </axisInfo>
      <parameter>
        <parameterNumber>1000</parameterNumber>
        <parameterValue>0</parameterValue>
      </parameter>
      <parameter>
        <parameterNumber>1001</parameterNumber>
        <parameterValue>0</parameterValue>
      </parameter>
      <parameter>
        <parameterNumber>1004</parameterNumber>
        <parameterValue>-2.33</parameterValue>
      </parameter>
      <parameter>
        <parameterNumber>1010</parameterNumber>
        <parameterValue>0</parameterValue>
      </parameter>
      <parameter>
        <parameterNumber>1011</parameterNumber>
        <parameterValue>0</parameterValue>
      </parameter>
      <parameter>
        <parameterNumber>1014</parameterNumber>
        <parameterValue>0</parameterValue>
      </parameter>
      <parameter>
        <parameterNumber>1017</parameterNumber>
        <parameterValue>50</parameterValue>
      </parameter>
      <parameter>
        <parameterNumber>1002</parameterNumber>
        <parameterValue>0</parameterValue>
      </parameter>
      <parameter>
        <parameterNumber>1200</parameterNumber>
        <parameterValue>-1.797693E+308</parameterValue>
      </parameter>
      <parameter>
        <parameterNumber>1201</parameterNumber>
        <parameterValue>1.797693E+308</parameterValue>
      </parameter>
      <parameter>
        <parameterNumber>1300</parameterNumber>
        <parameterValue>0</parameterValue>
      </parameter>
      <parameter>
        <parameterNumber>1301</parameterNumber>
        <parameterValue>0.1</parameterValue>
      </parameter>
      <parameter>
        <parameterNumber>1310</parameterNumber>
        <parameterValue>1</parameterValue>
      </parameter>
      <parameter>
        <parameterNumber>1311</parameterNumber>
        <parameterValue>0</parameterValue>
      </parameter>
      <parameter>
        <parameterNumber>1802</parameterNumber>
        <parameterValue>2044</parameterValue>
      </parameter>
      <parameter>
        <parameterNumber>1007</parameterNumber>
        <parameterValue>1</parameterValue>
      </parameter>
      <parameter>
        <parameterNumber>1008</parameterNumber>
        <parameterValue>360</parameterValue>
      </parameter>
      <parameter>
        <parameterNumber>1009</parameterNumber>
        <parameterValue>AXIS10</parameterValue>
      </parameter>
      <parameter>
        <parameterNumber>1013</parameterNumber>
        <parameterValue>4</parameterValue>
      </parameter>
      <parameter>
        <parameterNumber>1015</parameterNumber>
        <parameterValue>1</parameterValue>
      </parameter>
      <parameter>
        <parameterNumber>1016</parameterNumber>
        <parameterValue>50</parameterValue>
      </parameter>
      <parameter>
        <parameterNumber>1018</parameterNumber>
        <parameterValue>10</parameterValue>
      </parameter>
      <parameter>
        <parameterNumber>1019</parameterNumber>
        <parameterValue>SGDV-R90F21A002000</parameterValue>
      </parameter>
      <parameter>
        <parameterNumber>1020</parameterNumber>
        <parameterValue>0</parameterValue>
      </parameter>
      <parameter>
        <parameterNumber>1021</parameterNumber>
        <parameterValue>rotary</parameterValue>
      </parameter>
      <parameter>
        <parameterNumber>1022</parameterNumber>
        <parameterValue>100</parameterValue>
      </parameter>
      <parameter>
        <parameterNumber>1023</parameterNumber>
        <parameterValue>SGMJV-01A3A61</parameterValue>
      </parameter>
      <parameter>
        <parameterNumber>1024</parameterNumber>
        <parameterValue>rotary</parameterValue>
      </parameter>
      <parameter>
        <parameterNumber>1025</parameterNumber>
        <parameterValue>100</parameterValue>
      </parameter>
      <parameter>
        <parameterNumber>1026</parameterNumber>
        <parameterValue>absolute</parameterValue>
      </parameter>
      <parameter>
        <parameterNumber>1027</parameterNumber>
        <parameterValue>1048576</parameterValue>
      </parameter>
      <parameter>
        <parameterNumber>1028</parameterNumber>
        <parameterValue>1</parameterValue>
      </parameter>
      <parameter>
        <parameterNumber>1031</parameterNumber>
        <parameterValue>10</parameterValue>
      </parameter>
      <parameter>
        <parameterNumber>1033</parameterNumber>
        <parameterValue>360</parameterValue>
      </parameter>
      <parameter>
        <parameterNumber>1034</parameterNumber>
        <parameterValue>4</parameterValue>
      </parameter>
      <parameter>
        <parameterNumber>1035</parameterNumber>
        <parameterValue>0</parameterValue>
      </parameter>
      <parameter>
        <parameterNumber>1036</parameterNumber>
        <parameterValue>0.318000000</parameterValue>
      </parameter>
      <parameter>
        <parameterNumber>1037</parameterNumber>
        <parameterValue>3000</parameterValue>
      </parameter>
      <parameter>
        <parameterNumber>1048</parameterNumber>
        <parameterValue>0</parameterValue>
      </parameter>
      <parameter>
        <parameterNumber>2020</parameterNumber>
        <parameterValue>0</parameterValue>
      </parameter>
      <parameter>
        <parameterNumber>2028</parameterNumber>
        <parameterValue>300</parameterValue>
      </parameter>
    </axisControllerParameters>
  </axisParameters>
</controllerConfig>